pyrpiic/__init__.py
pyrpiic/clock/__init__.py
pyrpiic/clock/clock.py
pyrpiic/clock/defs.py
pyrpiic/clock/lmk61e2.py
pyrpiic/clock/si570.py
pyrpiic/clock/utils.py
pyrpiic/eeprom/__init__.py
pyrpiic/eeprom/eeprom.py
pyrpiic/eeprom/instances.py
pyrpiic/ioexpander/__init__.py
pyrpiic/ioexpander/pca9698.py
pyrpiic/ioexpander/tca6416a.py
pyrpiic/ioexpander/tca9535a.py
pyrpiic/mux/__init__.py
pyrpiic/mux/pca9543a.py
pyrpiic/sensor/__init__.py
pyrpiic/sensor/hdc1080.py
pyrpiic/sensor/ldc141x.py
pyrpiic/sensor/ldc161x.py
pyrpiic/sensor/ldc1x1y.py
pyrpiic/sensor/pca9685.py
pyrpiic-1.4.0.dist-info/LICENSE.md
pyrpiic-1.4.0.dist-info/WHEEL
pyrpiic-1.4.0.dist-info/METADATA
pyrpiic-1.4.0.dist-info/RECORD
