Metadata-Version: 2.1
Name: pyrpiic
Version: 1.4.0
Summary: Python RPI interface to low-level ICs
Home-page: https://github.com/Samtec-ASH/pyrpiic
License: MIT
Author: Adam Page
Author-email: adam.page@samtec.com
Requires-Python: >=3.7,<4.0
Classifier: License :: OSI Approved :: MIT License
Classifier: Programming Language :: Python :: 3
Classifier: Programming Language :: Python :: 3.7
Classifier: Programming Language :: Python :: 3.8
Classifier: Programming Language :: Python :: 3.9
Requires-Dist: PyRPIO (>=0.4.0,<0.5.0)
Requires-Dist: bitarray (>=2.2.5,<3.0.0)
Project-URL: Repository, https://github.com/Samtec-ASH/pyrpiic
